consgfx/consgfx_ext.cpython-310-x86_64-linux-gnu.so
consgfx/__init__.py
consgfx/consgfx_ext.pyi
consgfx-0.0.2.dist-info/WHEEL
consgfx-0.0.2.dist-info/RECORD
consgfx-0.0.2.dist-info/METADATA
