Metadata-Version: 2.1
Name: consgfx
Version: 0.0.2
Summary: Python console graphics display with Sixels and Kitty
Author-Email: Janne Hellsten <jjhellst@gmail.com>
Classifier: License :: OSI Approved :: BSD License
Project-URL: Homepage, https://github.com/nurpax/consgfx
Requires-Python: >=3.8
